{"hits":{"hits":[{"updated":"2021-03-19T16:52:48.258681+00:00","id":"357938","links":{"bibtex":"https://inspirehep.net/api/literature/357938?format=bibtex","latex-eu":"https://inspirehep.net/api/literature/357938?format=latex-eu","latex-us":"https://inspirehep.net/api/literature/357938?format=latex-us","json":"https://inspirehep.net/api/literature/357938?format=json","citations":"https://inspirehep.net/api/literature/?q=refersto%3Arecid%3A357938"},"metadata":{"report_numbers":[{"value":"CERN-PPE-93-113"},{"value":"FSU-SCRI-93-125"}],"publication_info":[{"journal_volume":"313","page_end":"563","year":1993,"page_start":"549","journal_title":"Phys.Lett.B"}],"texkeys":["Buskulic:1993kb"],"keywords":[{"schema":"INSPIRE","value":"electron positron: colliding beams"},{"schema":"INSPIRE","value":"colliding beams: electron positron"},{"schema":"INSPIRE","value":"electron positron: annihilation"},{"schema":"INSPIRE","value":"annihilation: electron positron"},{"schema":"INSPIRE","value":"Z0: electroproduction"},{"schema":"INSPIRE","value":"electroproduction: Z0"},{"schema":"INSPIRE","value":"Z0: nonleptonic decay"},{"schema":"INSPIRE","value":"nonleptonic decay: Z0"},{"schema":"INSPIRE","value":"Z0: branching ratio"},{"schema":"INSPIRE","value":"heavy quark"},{"schema":"INSPIRE","value":"quark: pair production"},{"schema":"INSPIRE","value":"pair production: quark"},{"schema":"INSPIRE","value":"hadron: multiple production"},{"schema":"INSPIRE","value":"multiple production: hadron"},{"schema":"INSPIRE","value":"final state: (lepton)"},{"schema":"INSPIRE","value":"(lepton): final state"},{"schema":"INSPIRE","value":"transverse momentum: high"},{"schema":"INSPIRE","value":"event shape analysis"},{"schema":"INSPIRE","value":"neural network"},{"schema":"INSPIRE","value":"ALEPH"},{"schema":"INSPIRE","value":"experimental results"},{"schema":"INSPIRE","value":"CERN LEP Stor"},{"schema":"INSPIRE","value":"approx. 91 GeV-cms"}],"collaborations":[{"value":"ALEPH"}],"control_number":357938,"dois":[{"value":"10.1016/0370-2693(93)90029-H"}],"preprint_date":"1993-07","titles":[{"title":"Measurement of the ratio Gamma (b anti-b) / Gamma (hadron) using event shape variables"}],"external_system_identifiers":[{"schema":"ADS","value":"1993PhLB..313..549B"},{"schema":"CDS","value":"251563"},{"schema":"SPIRES","value":"SPIRES-2807548"}]},"created":"1993-09-10T00:00:00+00:00"},{"updated":"2021-03-19T16:52:43.096654+00:00","id":"357424","links":{"bibtex":"https://inspirehep.net/api/literature/357424?format=bibtex","latex-eu":"https://inspirehep.net/api/literature/357424?format=latex-eu","latex-us":"https://inspirehep.net/api/literature/357424?format=latex-us","json":"https://inspirehep.net/api/literature/357424?format=json","citations":"https://inspirehep.net/api/literature/?q=refersto%3Arecid%3A357424"},"metadata":{"report_numbers":[{"value":"CERN-PPE-93-116"},{"value":"FSU-SCRI-93-134"}],"publication_info":[{"journal_volume":"314","page_end":"470","year":1993,"page_start":"459","journal_title":"Phys.Lett.B"}],"texkeys":["Buskulic:1993gj"],"keywords":[{"schema":"PDG","source":"PDG","value":"S051T"},{"schema":"INSPIRE","value":"electron positron: colliding beams"},{"schema":"INSPIRE","value":"colliding beams: electron positron"},{"schema":"INSPIRE","value":"electron positron: annihilation"},{"schema":"INSPIRE","value":"annihilation: electron positron"},{"schema":"INSPIRE","value":"Z0: electroproduction"},{"schema":"INSPIRE","value":"electroproduction: Z0"},{"schema":"INSPIRE","value":"Z0: nonleptonic decay"},{"schema":"INSPIRE","value":"nonleptonic decay: Z0"},{"schema":"INSPIRE","value":"bottom: pair production"},{"schema":"INSPIRE","value":"pair production: bottom"},{"schema":"INSPIRE","value":"bottom particle: lifetime"},{"schema":"INSPIRE","value":"track data analysis: vertex"},{"schema":"INSPIRE","value":"track data analysis: dipole"},{"schema":"INSPIRE","value":"ALEPH"},{"schema":"INSPIRE","value":"experimental results"},{"schema":"INSPIRE","value":"CERN LEP Stor"},{"schema":"INSPIRE","value":"approx. 91 GeV"}],"collaborations":[{"value":"ALEPH"}],"control_number":357424,"dois":[{"value":"10.1016/0370-2693(93)91265-O"}],"preprint_date":"1993-07","titles":[{"title":"Measurement of the b hadron lifetime with the dipole method"}],"external_system_identifiers":[{"schema":"CDS","value":"251565"},{"schema":"SPIRES","value":"SPIRES-2800900"}]},"created":"1993-08-24T00:00:00+00:00"},{"updated":"2021-03-19T16:52:42.636696+00:00","id":"357423","links":{"bibtex":"https://inspirehep.net/api/literature/357423?format=bibtex","latex-eu":"https://inspirehep.net/api/literature/357423?format=latex-eu","latex-us":"https://inspirehep.net/api/literature/357423?format=latex-us","json":"https://inspirehep.net/api/literature/357423?format=json","citations":"https://inspirehep.net/api/literature/?q=refersto%3Arecid%3A357423"},"metadata":{"report_numbers":[{"value":"CERN-PPE-93-111"},{"value":"FSU-SCRI-93-121"}],"publication_info":[{"journal_volume":"313","page_end":"325","year":1993,"page_start":"312","journal_title":"Phys.Lett.B"}],"texkeys":["Buskulic:1993gi"],"keywords":[{"schema":"INSPIRE","value":"electron positron: colliding beams"},{"schema":"INSPIRE","value":"colliding beams: electron positron"},{"schema":"INSPIRE","value":"electron positron: annihilation"},{"schema":"INSPIRE","value":"annihilation: electron positron"},{"schema":"INSPIRE","value":"Z0: electroproduction"},{"schema":"INSPIRE","value":"electroproduction: Z0"},{"schema":"INSPIRE","value":"Z0: associated production"},{"schema":"INSPIRE","value":"associated production: Z0"},{"schema":"INSPIRE","value":"Z0: decay modes"},{"schema":"INSPIRE","value":"decay modes: Z0"},{"schema":"INSPIRE","value":"Higgs particle: electroproduction"},{"schema":"INSPIRE","value":"electroproduction: Higgs particle"},{"schema":"INSPIRE","value":"Higgs particle: search for"},{"schema":"INSPIRE","value":"Higgs particle: decay modes"},{"schema":"INSPIRE","value":"decay modes: Higgs particle"},{"schema":"INSPIRE","value":"Higgs particle: branching ratio"},{"schema":"INSPIRE","value":"Higgs particle: mass"},{"schema":"INSPIRE","value":"mass: Higgs particle"},{"schema":"INSPIRE","value":"supersymmetry"},{"schema":"INSPIRE","value":"cross section: upper limit"},{"schema":"INSPIRE","value":"ALEPH"},{"schema":"INSPIRE","value":"experimental results"},{"schema":"INSPIRE","value":"CERN LEP Stor"},{"schema":"INSPIRE","value":"electron positron --> Higgs particle Z0"},{"schema":"INSPIRE","value":"approx. 91 GeV-cms"}],"collaborations":[{"value":"ALEPH"}],"control_number":357423,"dois":[{"value":"10.1016/0370-2693(93)91228-F"}],"preprint_date":"1993-07","titles":[{"title":"Search for a nonminimal Higgs boson produced in the reaction $e^{+} e^{-} \\to$ h $Z^{*}$"},{"source":"arXiv","title":"Search for a nonminimal Higgs boson produced in the reaction e+ e- ---> h Z*"}],"external_system_identifiers":[{"schema":"ADS","value":"1993PhLB..313..312B"},{"schema":"CDS","value":"251279"},{"schema":"SPIRES","value":"SPIRES-2800896"}]},"created":"1993-08-24T00:00:00+00:00"},{"updated":"2021-03-19T16:52:42.193448+00:00","id":"357422","links":{"bibtex":"https://inspirehep.net/api/literature/357422?format=bibtex","latex-eu":"https://inspirehep.net/api/literature/357422?format=latex-eu","latex-us":"https://inspirehep.net/api/literature/357422?format=latex-us","json":"https://inspirehep.net/api/literature/357422?format=json","citations":"https://inspirehep.net/api/literature/?q=refersto%3Arecid%3A357422"},"metadata":{"report_numbers":[{"value":"CERN-PPE-93-110"},{"value":"FSU-SCRI-93-120"}],"publication_info":[{"journal_volume":"313","page_end":"311","year":1993,"page_start":"299","journal_title":"Phys.Lett.B"}],"texkeys":["Buskulic:1993gf"],"keywords":[{"schema":"INSPIRE","value":"electron positron: colliding beams"},{"schema":"INSPIRE","value":"colliding beams: electron positron"},{"schema":"INSPIRE","value":"electron positron: annihilation"},{"schema":"INSPIRE","value":"annihilation: electron positron"},{"schema":"INSPIRE","value":"Higgs particle: electroproduction"},{"schema":"INSPIRE","value":"electroproduction: Higgs particle"},{"schema":"INSPIRE","value":"Higgs particle: mass"},{"schema":"INSPIRE","value":"mass: Higgs particle"},{"schema":"INSPIRE","value":"Higgs particle: decay modes"},{"schema":"INSPIRE","value":"decay modes: Higgs particle"},{"schema":"INSPIRE","value":"Higgs particle: branching ratio"},{"schema":"INSPIRE","value":"hadron: multiple production"},{"schema":"INSPIRE","value":"multiple production: hadron"},{"schema":"INSPIRE","value":"Z0: electroproduction"},{"schema":"INSPIRE","value":"electroproduction: Z0"},{"schema":"INSPIRE","value":"Z0: associated production"},{"schema":"INSPIRE","value":"associated production: Z0"},{"schema":"INSPIRE","value":"Z0: decay modes"},{"schema":"INSPIRE","value":"decay modes: Z0"},{"schema":"INSPIRE","value":"event shape analysis: planarity"},{"schema":"INSPIRE","value":"neutrino: missing-energy"},{"schema":"INSPIRE","value":"mass spectrum"},{"schema":"INSPIRE","value":"ALEPH"},{"schema":"INSPIRE","value":"experimental results"},{"schema":"INSPIRE","value":"CERN LEP Stor"},{"schema":"INSPIRE","value":"electron positron --> Higgs particle Z0"},{"schema":"INSPIRE","value":"approx. 91 GeV-cms"}],"collaborations":[{"value":"ALEPH"}],"control_number":357422,"dois":[{"value":"10.1016/0370-2693(93)91227-E"}],"preprint_date":"1993-07","titles":[{"title":"Search for the Standard Model Higgs boson"},{"source":"arXiv","title":"Search for the Standard Model Higgs boson"}],"external_system_identifiers":[{"schema":"ADS","value":"1993PhLB..313..299B"},{"schema":"CDS","value":"251277"},{"schema":"SPIRES","value":"SPIRES-2800861"}]},"created":"1993-09-10T00:00:00+00:00"},{"updated":"2021-03-19T16:52:49.490908+00:00","id":"357941","links":{"bibtex":"https://inspirehep.net/api/literature/357941?format=bibtex","latex-eu":"https://inspirehep.net/api/literature/357941?format=latex-eu","latex-us":"https://inspirehep.net/api/literature/357941?format=latex-us","json":"https://inspirehep.net/api/literature/357941?format=json","citations":"https://inspirehep.net/api/literature/?q=refersto%3Arecid%3A357941"},"metadata":{"report_numbers":[{"value":"CERN-PPE-93-120"},{"value":"FSU-SCRI-93-123"}],"publication_info":[{"journal_volume":"313","page_end":"534","year":1993,"page_start":"520","journal_title":"Phys.Lett.B"}],"texkeys":["Buskulic:1993ke"],"keywords":[{"schema":"PDG","source":"PDG","value":"S007NI"},{"schema":"PDG","source":"PDG","value":"S044:Desig=9"},{"schema":"INSPIRE","value":"electron positron: colliding beams"},{"schema":"INSPIRE","value":"colliding beams: electron positron"},{"schema":"INSPIRE","value":"electron positron: annihilation"},{"schema":"INSPIRE","value":"annihilation: electron positron"},{"schema":"INSPIRE","value":"Z0: electroproduction"},{"schema":"INSPIRE","value":"electroproduction: Z0"},{"schema":"INSPIRE","value":"Z0: width"},{"schema":"INSPIRE","value":"final state: (1photon)"},{"schema":"INSPIRE","value":"(1photon): final state"},{"schema":"INSPIRE","value":"neutrino: flavor"},{"schema":"INSPIRE","value":"background"},{"schema":"INSPIRE","value":"cross section: energy dependence"},{"schema":"INSPIRE","value":"ALEPH"},{"schema":"INSPIRE","value":"experimental results"},{"schema":"INSPIRE","value":"CERN LEP Stor"},{"schema":"INSPIRE","value":"electron positron --> neutrino antineutrino photon"},{"schema":"INSPIRE","value":"88.25-94.25 GeV-cms"}],"collaborations":[{"value":"ALEPH"}],"control_number":357941,"dois":[{"value":"10.1016/0370-2693(93)90027-F"}],"preprint_date":"1993-07","titles":[{"title":"A Direct measurement of the invisible width of the Z from single photon counting"}],"external_system_identifiers":[{"schema":"CDS","value":"251845"},{"schema":"SPIRES","value":"SPIRES-2807572"}]},"created":"1993-09-10T00:00:00+00:00"},{"updated":"2021-03-19T16:52:38.737862+00:00","id":"356731","links":{"bibtex":"https://inspirehep.net/api/literature/356731?format=bibtex","latex-eu":"https://inspirehep.net/api/literature/356731?format=latex-eu","latex-us":"https://inspirehep.net/api/literature/356731?format=latex-us","json":"https://inspirehep.net/api/literature/356731?format=json","citations":"https://inspirehep.net/api/literature/?q=refersto%3Arecid%3A356731"},"metadata":{"report_numbers":[{"value":"CERN-PPE-93-94"},{"value":"FSU-SCRI-93-141"}],"publication_info":[{"journal_volume":"313","page_end":"519","year":1993,"page_start":"509","journal_title":"Phys.Lett.B"}],"texkeys":["Buskulic:1993mm"],"keywords":[{"schema":"INSPIRE","value":"electron positron: colliding beams"},{"schema":"INSPIRE","value":"colliding beams: electron positron"},{"schema":"INSPIRE","value":"exchange: two-photon"},{"schema":"INSPIRE","value":"two-photon: exchange"},{"schema":"INSPIRE","value":"photon photon: interaction"},{"schema":"INSPIRE","value":"interaction: photon photon"},{"schema":"INSPIRE","value":"hadron: multiple production"},{"schema":"INSPIRE","value":"multiple production: hadron"},{"schema":"INSPIRE","value":"jet: multiple production"},{"schema":"INSPIRE","value":"multiple production: jet"},{"schema":"INSPIRE","value":"transverse momentum dependence"},{"schema":"INSPIRE","value":"vector dominance"},{"schema":"INSPIRE","value":"photon: structure function"},{"schema":"INSPIRE","value":"hard scattering"},{"schema":"INSPIRE","value":"charged particle: multiplicity"},{"schema":"INSPIRE","value":"quantum chromodynamics"},{"schema":"INSPIRE","value":"cross section: hadronic"},{"schema":"INSPIRE","value":"ALEPH"},{"schema":"INSPIRE","value":"experimental results"},{"schema":"INSPIRE","value":"CERN LEP Stor"},{"schema":"INSPIRE","value":"88-95 GeV-cms"}],"collaborations":[{"value":"ALEPH"}],"control_number":356731,"dois":[{"value":"10.1016/0370-2693(93)90026-E"}],"preprint_date":"1993-06","titles":[{"title":"An Experimental study of gamma gamma ---> hadrons at LEP"}],"external_system_identifiers":[{"schema":"ADS","value":"1993PhLB..313..509B"},{"schema":"CDS","value":"250663"},{"schema":"SPIRES","value":"SPIRES-2790602"}]},"created":"1993-08-02T00:00:00+00:00"},{"updated":"2021-03-19T16:52:47.814714+00:00","id":"357937","links":{"bibtex":"https://inspirehep.net/api/literature/357937?format=bibtex","latex-eu":"https://inspirehep.net/api/literature/357937?format=latex-eu","latex-us":"https://inspirehep.net/api/literature/357937?format=latex-us","json":"https://inspirehep.net/api/literature/357937?format=json","citations":"https://inspirehep.net/api/literature/?q=refersto%3Arecid%3A357937"},"metadata":{"report_numbers":[{"value":"CERN-PPE-93-108"},{"value":"FSU-SCRI-93-124"}],"publication_info":[{"journal_volume":"313","page_end":"548","year":1993,"page_start":"535","journal_title":"Phys.Lett.B"},{"pubinfo_freetext":"Phys. Lett. B313 (1993) 535-548 and CERN Geneva - CERN-PPE-93-108 (93/06,rec.Sep.) 16 p"}],"texkeys":["Buskulic:1993ka"],"keywords":[{"schema":"INSPIRE","value":"electron positron: colliding beams"},{"schema":"INSPIRE","value":"colliding beams: electron positron"},{"schema":"INSPIRE","value":"electron positron: annihilation"},{"schema":"INSPIRE","value":"annihilation: electron positron"},{"schema":"INSPIRE","value":"Z0: electroproduction"},{"schema":"INSPIRE","value":"electroproduction: Z0"},{"schema":"INSPIRE","value":"Z0: nonleptonic decay"},{"schema":"INSPIRE","value":"nonleptonic decay: Z0"},{"schema":"INSPIRE","value":"Z0: branching ratio"},{"schema":"INSPIRE","value":"bottom"},{"schema":"INSPIRE","value":"quark: pair production"},{"schema":"INSPIRE","value":"pair production: quark"},{"schema":"INSPIRE","value":"hadron: multiple production"},{"schema":"INSPIRE","value":"multiple production: hadron"},{"schema":"INSPIRE","value":"bottom particle: lifetime"},{"schema":"INSPIRE","value":"track data analysis: impact parameter"},{"schema":"INSPIRE","value":"mass: top"},{"schema":"INSPIRE","value":"top: mass"},{"schema":"INSPIRE","value":"correlation"},{"schema":"INSPIRE","value":"semiconductor detector: vertex"},{"schema":"INSPIRE","value":"ALEPH"},{"schema":"INSPIRE","value":"experimental results"},{"schema":"INSPIRE","value":"CERN LEP Stor"},{"schema":"INSPIRE","value":"approx. 91 GeV-cms"}],"collaborations":[{"value":"ALEPH"}],"control_number":357937,"dois":[{"value":"10.1016/0370-2693(93)90028-G"}],"preprint_date":"1993-06","titles":[{"title":"A Precise measurement of Gamma ($Z \\to b \\bar{b}$) / Gamma ($Z \\to$ hadrons)"},{"source":"arXiv","title":"A Precise measurement of Gamma (Z ---> b anti-b) / Gamma (Z ---> hadrons)"}],"external_system_identifiers":[{"schema":"ADS","value":"1993PhLB..313..535B"},{"schema":"CDS","value":"251363"},{"schema":"SPIRES","value":"SPIRES-2807530"}]},"created":"1993-09-10T00:00:00+00:00"},{"updated":"2021-03-19T16:52:44.372736+00:00","id":"357822","links":{"bibtex":"https://inspirehep.net/api/literature/357822?format=bibtex","latex-eu":"https://inspirehep.net/api/literature/357822?format=latex-eu","latex-us":"https://inspirehep.net/api/literature/357822?format=latex-us","json":"https://inspirehep.net/api/literature/357822?format=json","citations":"https://inspirehep.net/api/literature/?q=refersto%3Arecid%3A357822"},"metadata":{"report_numbers":[{"value":"CERN-PPE-93-97"}],"publication_info":[{"journal_volume":"311","page_end":"430","year":1993,"page_start":"425","journal_title":"Phys.Lett.B"},{"journal_volume":"316","artid":"631","material":"erratum","year":1993,"page_start":"631","journal_title":"Phys.Lett.B"},{"pubinfo_freetext":"Phys. Lett. B316 (1993) 631. (Phys. Lett. B311 (1993) 425-436) and CERN Geneva - CERN-PPE-93-097 (93/06,rec.Sep.) 12 p"}],"texkeys":["Buskulic:1993dr"],"keywords":[{"schema":"PDG","source":"PDG","value":"S086:Desig=6"},{"schema":"PDG","source":"PDG","value":"S086:Desig=5"},{"schema":"PDG","source":"PDG","value":"S086M"},{"schema":"INSPIRE","value":"electron positron: colliding beams"},{"schema":"INSPIRE","value":"colliding beams: electron positron"},{"schema":"INSPIRE","value":"electron positron: annihilation"},{"schema":"INSPIRE","value":"annihilation: electron positron"},{"schema":"INSPIRE","value":"Z0: electroproduction"},{"schema":"INSPIRE","value":"electroproduction: Z0"},{"schema":"INSPIRE","value":"Z0: nonleptonic decay"},{"schema":"INSPIRE","value":"nonleptonic decay: Z0"},{"schema":"INSPIRE","value":"ALEPH"},{"schema":"INSPIRE","value":"experimental results"},{"schema":"INSPIRE","value":"CERN LEP Stor"},{"schema":"INSPIRE","value":"approx. 91 GeV-cms"},{"schema":"INSPIRE","value":"B/s: mass"},{"schema":"INSPIRE","value":"mass: B/s"},{"schema":"INSPIRE","value":"B/s: decay modes"},{"schema":"INSPIRE","value":"decay modes: B/s"}],"collaborations":[{"value":"ALEPH"}],"control_number":357822,"dois":[{"value":"10.1016/0370-2693(93)90588-9"}],"preprint_date":"1993-06","titles":[{"title":"First measurement of the B(S) meson mass"}],"external_system_identifiers":[{"schema":"CDS","value":"250666"},{"schema":"SPIRES","value":"SPIRES-2806002"}]},"created":"1993-09-08T00:00:00+00:00"},{"updated":"2021-03-19T16:52:50.132846+00:00","id":"357751","links":{"bibtex":"https://inspirehep.net/api/literature/357751?format=bibtex","latex-eu":"https://inspirehep.net/api/literature/357751?format=latex-eu","latex-us":"https://inspirehep.net/api/literature/357751?format=latex-us","json":"https://inspirehep.net/api/literature/357751?format=json","citations":"https://inspirehep.net/api/literature/?q=refersto%3Arecid%3A357751"},"metadata":{"report_numbers":[{"value":"CERN-PPE-93-99"},{"value":"FSU-SCRI-93-122"}],"publication_info":[{"journal_volume":"313","page_end":"508","year":1993,"page_start":"498","journal_title":"Phys.Lett.B"}],"texkeys":["Buskulic:1993zs"],"keywords":[{"schema":"PDG","source":"PDG","value":"S042D"},{"schema":"INSPIRE","value":"electron positron: colliding beams"},{"schema":"INSPIRE","value":"colliding beams: electron positron"},{"schema":"INSPIRE","value":"electron positron: annihilation"},{"schema":"INSPIRE","value":"annihilation: electron positron"},{"schema":"INSPIRE","value":"B0: electroproduction"},{"schema":"INSPIRE","value":"electroproduction: B0"},{"schema":"INSPIRE","value":"lepton: associated production"},{"schema":"INSPIRE","value":"associated production: lepton"},{"schema":"INSPIRE","value":"B0 anti-B0: mixing"},{"schema":"INSPIRE","value":"interference: time dependence"},{"schema":"INSPIRE","value":"mass difference: (B0 anti-B0)"},{"schema":"INSPIRE","value":"(B0 anti-B0): mass difference"},{"schema":"INSPIRE","value":"B0: decay modes"},{"schema":"INSPIRE","value":"decay modes: B0"},{"schema":"INSPIRE","value":"lepton: charge correlation"},{"schema":"INSPIRE","value":"D*(2010): decay modes"},{"schema":"INSPIRE","value":"decay modes: D*(2010)"},{"schema":"INSPIRE","value":"background"},{"schema":"INSPIRE","value":"ALEPH"},{"schema":"INSPIRE","value":"experimental results"},{"schema":"INSPIRE","value":"CERN LEP Stor"},{"schema":"INSPIRE","value":"B0 --> D*(2010) anything"},{"schema":"INSPIRE","value":"approx. 91 GeV-cms"}],"collaborations":[{"value":"ALEPH"}],"control_number":357751,"dois":[{"value":"10.1016/0370-2693(93)90025-D"}],"preprint_date":"1993-06","titles":[{"title":"Observation of the time dependence of B(d)0 - anti-B(d)0 mixing"}],"external_system_identifiers":[{"schema":"CDS","value":"251278"},{"schema":"SPIRES","value":"SPIRES-2805057"}]},"created":"1993-09-03T00:00:00+00:00"},{"updated":"2021-03-19T16:52:38.127583+00:00","id":"356730","links":{"bibtex":"https://inspirehep.net/api/literature/356730?format=bibtex","latex-eu":"https://inspirehep.net/api/literature/356730?format=latex-eu","latex-us":"https://inspirehep.net/api/literature/356730?format=latex-us","json":"https://inspirehep.net/api/literature/356730?format=json","citations":"https://inspirehep.net/api/literature/?q=refersto%3Arecid%3A356730"},"metadata":{"report_numbers":[{"value":"CERN-PPE-93-75"}],"publication_info":[{"journal_volume":"308","artid":"425","year":1993,"page_start":"425","journal_title":"Phys.Lett.B"}],"texkeys":["Buskulic:1993mk"],"keywords":[{"schema":"PDG","source":"PDG","value":"S056ZFR"},{"schema":"INSPIRE","value":"electron positron: colliding beams"},{"schema":"INSPIRE","value":"colliding beams: electron positron"},{"schema":"INSPIRE","value":"electron positron: annihilation"},{"schema":"INSPIRE","value":"annihilation: electron positron"},{"schema":"INSPIRE","value":"fermion: pair production"},{"schema":"INSPIRE","value":"pair production: fermion"},{"schema":"INSPIRE","value":"photon: pair production"},{"schema":"INSPIRE","value":"pair production: photon"},{"schema":"INSPIRE","value":"mass spectrum: (2photon)"},{"schema":"INSPIRE","value":"(2photon): mass spectrum"},{"schema":"INSPIRE","value":"resonance: width"},{"schema":"INSPIRE","value":"width: resonance"},{"schema":"INSPIRE","value":"upper limit"},{"schema":"INSPIRE","value":"ALEPH"},{"schema":"INSPIRE","value":"experimental results"},{"schema":"INSPIRE","value":"CERN LEP Stor"},{"schema":"INSPIRE","value":"electron positron --> quark antiquark 2photon"},{"schema":"INSPIRE","value":"electron positron --> lepton antilepton 2photon"},{"schema":"INSPIRE","value":"approx. 91 GeV-cms"}],"collaborations":[{"value":"ALEPH"}],"control_number":356730,"dois":[{"value":"10.1016/0370-2693(93)91308-A"}],"preprint_date":"1993-04","titles":[{"title":"Search for high mass photon pairs in e+ e- ---> f anti-f gamma gamma (f = e, mu, tau, neutrino, q) at LEP"}],"external_system_identifiers":[{"schema":"CDS","value":"249293"},{"schema":"SPIRES","value":"SPIRES-2790599"}]},"created":"1993-08-02T00:00:00+00:00"},{"updated":"2021-03-19T16:52:27.974614+00:00","id":"353690","links":{"bibtex":"https://inspirehep.net/api/literature/353690?format=bibtex","latex-eu":"https://inspirehep.net/api/literature/353690?format=latex-eu","latex-us":"https://inspirehep.net/api/literature/353690?format=latex-us","json":"https://inspirehep.net/api/literature/353690?format=json","citations":"https://inspirehep.net/api/literature/?q=refersto%3Arecid%3A353690"},"metadata":{"report_numbers":[{"value":"LAL-93-01"},{"value":"CERN-PPE-93-41"}],"publication_info":[{"journal_volume":"307","page_end":"220","year":1993,"page_start":"209","journal_title":"Phys.Lett.B"}],"texkeys":["Buskulic:1993sv"],"keywords":[{"schema":"INSPIRE","value":"electron positron: colliding beams"},{"schema":"INSPIRE","value":"colliding beams: electron positron"},{"schema":"INSPIRE","value":"electron positron: annihilation"},{"schema":"INSPIRE","value":"annihilation: electron positron"},{"schema":"INSPIRE","value":"tau: electroproduction"},{"schema":"INSPIRE","value":"electroproduction: tau"},{"schema":"INSPIRE","value":"tau: pair production"},{"schema":"INSPIRE","value":"pair production: tau"},{"schema":"INSPIRE","value":"tau: leptonic decay"},{"schema":"INSPIRE","value":"leptonic decay: tau"},{"schema":"INSPIRE","value":"tau: semileptonic decay"},{"schema":"INSPIRE","value":"semileptonic decay: tau"},{"schema":"INSPIRE","value":"tau: branching ratio"},{"schema":"INSPIRE","value":"tau: width"},{"schema":"INSPIRE","value":"mass spectrum: ((n)hadron)"},{"schema":"INSPIRE","value":"((n)hadron): mass spectrum"},{"schema":"INSPIRE","value":"strong interaction: coupling constant"},{"schema":"INSPIRE","value":"coupling constant: strong interaction"},{"schema":"INSPIRE","value":"effect: nonperturbative"},{"schema":"INSPIRE","value":"ALEPH"},{"schema":"INSPIRE","value":"experimental results"},{"schema":"INSPIRE","value":"CERN LEP Stor"},{"schema":"INSPIRE","value":"approx. 91 GeV-cms"}],"collaborations":[{"value":"ALEPH"}],"control_number":353690,"dois":[{"value":"10.1016/0370-2693(93)90212-Z"}],"preprint_date":"1993-03","titles":[{"title":"Measurement of the strong coupling constant using tau decays"}],"external_system_identifiers":[{"schema":"ADS","value":"1993PhLB..307..209B"},{"schema":"CDS","value":"247112"},{"schema":"SPIRES","value":"SPIRES-2728524"}]},"created":"1993-04-15T00:00:00+00:00"},{"updated":"2021-03-19T16:52:16.184498+00:00","id":"354144","links":{"bibtex":"https://inspirehep.net/api/literature/354144?format=bibtex","latex-eu":"https://inspirehep.net/api/literature/354144?format=latex-eu","latex-us":"https://inspirehep.net/api/literature/354144?format=latex-us","json":"https://inspirehep.net/api/literature/354144?format=json","citations":"https://inspirehep.net/api/literature/?q=refersto%3Arecid%3A354144"},"metadata":{"report_numbers":[{"value":"CERN-PPE-93-42"}],"publication_info":[{"journal_volume":"307","page_end":"208","year":1993,"page_start":"194","journal_title":"Phys.Lett.B"},{"journal_volume":"325","material":"erratum","page_end":"538","year":1994,"page_start":"537","journal_title":"Phys.Lett.B"}],"texkeys":["Buskulic:1993vi"],"keywords":[{"schema":"PDG","source":"PDG","value":"S042DT1"},{"schema":"PDG","source":"PDG","value":"S042T"},{"schema":"PDG","source":"PDG","value":"S041T"},{"schema":"INSPIRE","value":"electron positron: colliding beams"},{"schema":"INSPIRE","value":"colliding beams: electron positron"},{"schema":"INSPIRE","value":"electron positron: annihilation"},{"schema":"INSPIRE","value":"annihilation: electron positron"},{"schema":"INSPIRE","value":"Z0: electroproduction"},{"schema":"INSPIRE","value":"electroproduction: Z0"},{"schema":"INSPIRE","value":"Z0: nonleptonic decay"},{"schema":"INSPIRE","value":"nonleptonic decay: Z0"},{"schema":"INSPIRE","value":"B: semileptonic decay"},{"schema":"INSPIRE","value":"semileptonic decay: B"},{"schema":"INSPIRE","value":"anti-B0: lifetime"},{"schema":"INSPIRE","value":"B-: lifetime"},{"schema":"INSPIRE","value":"lifetime: ratio"},{"schema":"INSPIRE","value":"B: path length"},{"schema":"INSPIRE","value":"B: branching ratio"},{"schema":"INSPIRE","value":"semiconductor detector: vertex"},{"schema":"INSPIRE","value":"ALEPH"},{"schema":"INSPIRE","value":"experimental results"},{"schema":"INSPIRE","value":"CERN LEP Stor"},{"schema":"INSPIRE","value":"B- --> D0 lepton-"},{"schema":"INSPIRE","value":"anti-B0 --> D*(2010) lepton-"},{"schema":"INSPIRE","value":"88.2-94.2 GeV"}],"collaborations":[{"value":"ALEPH"}],"control_number":354144,"dois":[{"value":"10.1016/0370-2693(93)90211-Y"}],"preprint_date":"1993-03","titles":[{"title":"Measurement of the anti-B0 and B- meson lifetimes"}],"external_system_identifiers":[{"schema":"CDS","value":"247117"},{"schema":"SPIRES","value":"SPIRES-2740656"}]},"created":"1993-05-07T00:00:00+00:00"},{"updated":"2021-03-19T16:52:17.239258+00:00","id":"354146","links":{"bibtex":"https://inspirehep.net/api/literature/354146?format=bibtex","latex-eu":"https://inspirehep.net/api/literature/354146?format=latex-eu","latex-us":"https://inspirehep.net/api/literature/354146?format=latex-us","json":"https://inspirehep.net/api/literature/354146?format=json","citations":"https://inspirehep.net/api/literature/?q=refersto%3Arecid%3A354146"},"metadata":{"report_numbers":[{"value":"CERN-PPE-93-39"},{"value":"FSU-SCRI-93-117"}],"publication_info":[{"journal_volume":"59","page_end":"386","year":1993,"page_start":"369","journal_title":"Z.Phys.C"}],"texkeys":["Buskulic:1993vk"],"keywords":[{"schema":"INSPIRE","value":"electron positron: colliding beams"},{"schema":"INSPIRE","value":"colliding beams: electron positron"},{"schema":"INSPIRE","value":"electron positron: annihilation"},{"schema":"INSPIRE","value":"annihilation: electron positron"},{"schema":"INSPIRE","value":"Z0: electroproduction"},{"schema":"INSPIRE","value":"electroproduction: Z0"},{"schema":"INSPIRE","value":"tau: pair production"},{"schema":"INSPIRE","value":"pair production: tau"},{"schema":"INSPIRE","value":"tau: polarization"},{"schema":"INSPIRE","value":"polarization: tau"},{"schema":"INSPIRE","value":"angular dependence"},{"schema":"INSPIRE","value":"parametrization"},{"schema":"INSPIRE","value":"tau: leptonic decay"},{"schema":"INSPIRE","value":"leptonic decay: tau"},{"schema":"INSPIRE","value":"tau: semileptonic decay"},{"schema":"INSPIRE","value":"semileptonic decay: tau"},{"schema":"INSPIRE","value":"universality: (tau electron)"},{"schema":"INSPIRE","value":"Weinberg angle"},{"schema":"INSPIRE","value":"ALEPH"},{"schema":"INSPIRE","value":"experimental results"},{"schema":"INSPIRE","value":"CERN LEP Stor"},{"schema":"INSPIRE","value":"88.2-94.2 GeV"},{"schema":"INSPIRE","value":"tau --> electron neutrino/tau antineutrino/e"},{"schema":"INSPIRE","value":"tau --> muon- neutrino/tau antineutrino/mu"},{"schema":"INSPIRE","value":"tau --> pi neutrino/tau"},{"schema":"INSPIRE","value":"tau --> rho(770) neutrino/tau"},{"schema":"INSPIRE","value":"tau --> a1(1260) neutrino/tau"}],"collaborations":[{"value":"ALEPH"}],"control_number":354146,"dois":[{"value":"10.1007/BF01498618"}],"preprint_date":"1993-03","titles":[{"title":"Measurement of the tau polarization at the Z resonance"}],"external_system_identifiers":[{"schema":"CDS","value":"247108"},{"schema":"SPIRES","value":"SPIRES-2740672"}]},"created":"1993-05-07T00:00:00+00:00"},{"updated":"2021-03-19T16:52:30.147218+00:00","id":"354298","links":{"bibtex":"https://inspirehep.net/api/literature/354298?format=bibtex","latex-eu":"https://inspirehep.net/api/literature/354298?format=latex-eu","latex-us":"https://inspirehep.net/api/literature/354298?format=latex-us","json":"https://inspirehep.net/api/literature/354298?format=json","citations":"https://inspirehep.net/api/literature/?q=refersto%3Arecid%3A354298"},"metadata":{"report_numbers":[{"value":"CERN-PPE-93-40"},{"value":"FSU-SCRI-93-135"}],"publication_info":[{"journal_volume":"60","page_end":"82","year":1993,"page_start":"71","journal_title":"Z.Phys.C"}],"texkeys":["Buskulic:1993gu"],"keywords":[{"schema":"INSPIRE","value":"electron positron: colliding beams"},{"schema":"INSPIRE","value":"colliding beams: electron positron"},{"schema":"INSPIRE","value":"electron positron: annihilation"},{"schema":"INSPIRE","value":"annihilation: electron positron"},{"schema":"INSPIRE","value":"electroweak interaction: parametrization"},{"schema":"INSPIRE","value":"parametrization: electroweak interaction"},{"schema":"INSPIRE","value":"Z0: electroproduction"},{"schema":"INSPIRE","value":"electroproduction: Z0"},{"schema":"INSPIRE","value":"Z0: mass"},{"schema":"INSPIRE","value":"mass: Z0"},{"schema":"INSPIRE","value":"Z0: width"},{"schema":"INSPIRE","value":"Z0: leptonic decay"},{"schema":"INSPIRE","value":"leptonic decay: Z0"},{"schema":"INSPIRE","value":"Z0: nonleptonic decay"},{"schema":"INSPIRE","value":"nonleptonic decay: Z0"},{"schema":"INSPIRE","value":"cross section: hadronic"},{"schema":"INSPIRE","value":"fermion: pair production"},{"schema":"INSPIRE","value":"pair production: fermion"},{"schema":"INSPIRE","value":"angular distribution: asymmetry"},{"schema":"INSPIRE","value":"asymmetry: angular distribution"},{"schema":"INSPIRE","value":"energy dependence"},{"schema":"INSPIRE","value":"neutrino: flavor"},{"schema":"INSPIRE","value":"Weinberg angle"},{"schema":"INSPIRE","value":"coupling constant: vector"},{"schema":"INSPIRE","value":"vector: coupling constant"},{"schema":"INSPIRE","value":"coupling constant: axial-vector"},{"schema":"INSPIRE","value":"axial-vector: coupling constant"},{"schema":"INSPIRE","value":"coupling constant: strong interaction"},{"schema":"INSPIRE","value":"strong interaction: coupling constant"},{"schema":"INSPIRE","value":"mass: top"},{"schema":"INSPIRE","value":"top: mass"},{"schema":"INSPIRE","value":"ALEPH"},{"schema":"INSPIRE","value":"experimental results"},{"schema":"INSPIRE","value":"CERN LEP Stor"},{"schema":"INSPIRE","value":"88.25-94.25 GeV"}],"collaborations":[{"value":"ALEPH"}],"control_number":354298,"dois":[{"value":"10.1007/BF01650432"}],"preprint_date":"1993-03","titles":[{"title":"Update of electroweak parameters from $Z$ decays"},{"source":"arXiv","title":"Update of electroweak parameters from Z decays"}],"external_system_identifiers":[{"schema":"HEPDATA","value":"ins354298"},{"schema":"CDS","value":"247106"},{"schema":"SPIRES","value":"SPIRES-2743396"}]},"created":"1993-05-17T00:00:00+00:00"},{"updated":"2021-03-19T16:52:29.708977+00:00","id":"354297","links":{"bibtex":"https://inspirehep.net/api/literature/354297?format=bibtex","latex-eu":"https://inspirehep.net/api/literature/354297?format=latex-eu","latex-us":"https://inspirehep.net/api/literature/354297?format=latex-us","json":"https://inspirehep.net/api/literature/354297?format=json","citations":"https://inspirehep.net/api/literature/?q=refersto%3Arecid%3A354297"},"metadata":{"report_numbers":[{"value":"CERN-PPE-93-52"}],"publication_info":[{"journal_volume":"59","page_end":"230","year":1993,"page_start":"215","journal_title":"Z.Phys.C"}],"texkeys":["Buskulic:1993gs"],"keywords":[{"schema":"INSPIRE","value":"electron positron: colliding beams"},{"schema":"INSPIRE","value":"colliding beams: electron positron"},{"schema":"INSPIRE","value":"electron positron: annihilation"},{"schema":"INSPIRE","value":"annihilation: electron positron"},{"schema":"INSPIRE","value":"lepton: pair production"},{"schema":"INSPIRE","value":"pair production: lepton"},{"schema":"INSPIRE","value":"lepton: universality"},{"schema":"INSPIRE","value":"photon: pair production"},{"schema":"INSPIRE","value":"pair production: photon"},{"schema":"INSPIRE","value":"electroweak interaction: validity test"},{"schema":"INSPIRE","value":"validity test: electroweak interaction"},{"schema":"INSPIRE","value":"four-fermion interaction"},{"schema":"INSPIRE","value":"new interaction: effective Lagrangian"},{"schema":"INSPIRE","value":"effective Lagrangian: new interaction"},{"schema":"INSPIRE","value":"model: composite"},{"schema":"INSPIRE","value":"current: chiral"},{"schema":"INSPIRE","value":"amplitude analysis"},{"schema":"INSPIRE","value":"angular distribution"},{"schema":"INSPIRE","value":"ALEPH"},{"schema":"INSPIRE","value":"experimental results"},{"schema":"INSPIRE","value":"CERN LEP Stor"},{"schema":"INSPIRE","value":"electron positron --> lepton+ lepton-"},{"schema":"INSPIRE","value":"electron positron --> 2photon"},{"schema":"INSPIRE","value":"88.25-94.25 GeV"}],"collaborations":[{"value":"ALEPH"}],"control_number":354297,"dois":[{"value":"10.1007/BF01566686"}],"preprint_date":"1993-03","titles":[{"title":"Search for contact interactions in the reactions $e^{+} e^{-} \\to \\ell^+ \\ell^-$ and $e^{+} e^{-} \\to \\gamma \\gamma$"},{"source":"arXiv","title":"Search for contact interactions in the reactions e+ e- ---> lepton+ lepton- and e+ e- ---> gamma gamma"}],"external_system_identifiers":[{"schema":"CDS","value":"248135"},{"schema":"CERNKEY","value":"0164343"},{"schema":"SPIRES","value":"SPIRES-2743370"}]},"created":"1993-05-17T00:00:00+00:00"},{"updated":"2021-03-19T16:51:32.788232+00:00","id":"343700","links":{"bibtex":"https://inspirehep.net/api/literature/343700?format=bibtex","latex-eu":"https://inspirehep.net/api/literature/343700?format=latex-eu","latex-us":"https://inspirehep.net/api/literature/343700?format=latex-us","json":"https://inspirehep.net/api/literature/343700?format=json","citations":"https://inspirehep.net/api/literature/?q=refersto%3Arecid%3A343700"},"metadata":{"report_numbers":[{"value":"CERN-PPE-92-210"}],"publication_info":[{"journal_volume":"303","page_end":"208","year":1993,"page_start":"198","journal_title":"Phys.Lett.B"}],"texkeys":["Buskulic:1992mr"],"keywords":[{"schema":"PDG","source":"PDG","value":"S027FR"},{"schema":"PDG","source":"PDG","value":"S015EE"},{"schema":"INSPIRE","value":"electron positron: colliding beams"},{"schema":"INSPIRE","value":"colliding beams: electron positron"},{"schema":"INSPIRE","value":"electron positron: annihilation"},{"schema":"INSPIRE","value":"annihilation: electron positron"},{"schema":"INSPIRE","value":"Z0: electroproduction"},{"schema":"INSPIRE","value":"electroproduction: Z0"},{"schema":"INSPIRE","value":"Z0: leptonic decay"},{"schema":"INSPIRE","value":"leptonic decay: Z0"},{"schema":"INSPIRE","value":"Z0: nonleptonic decay"},{"schema":"INSPIRE","value":"nonleptonic decay: Z0"},{"schema":"INSPIRE","value":"new particle: search for"},{"schema":"INSPIRE","value":"ionization: energy loss"},{"schema":"INSPIRE","value":"charged particle: pair production"},{"schema":"INSPIRE","value":"pair production: charged particle"},{"schema":"INSPIRE","value":"charged particle: heavy"},{"schema":"INSPIRE","value":"charge: fractional"},{"schema":"INSPIRE","value":"cross section: production"},{"schema":"INSPIRE","value":"production: cross section"},{"schema":"INSPIRE","value":"upper limit"},{"schema":"INSPIRE","value":"ALEPH"},{"schema":"INSPIRE","value":"experimental results"},{"schema":"INSPIRE","value":"CERN LEP Stor"},{"schema":"INSPIRE","value":"approx. 91 GeV-cms"}],"collaborations":[{"value":"ALEPH"}],"control_number":343700,"dois":[{"value":"10.1016/0370-2693(93)90066-Q"}],"preprint_date":"1992-12","titles":[{"title":"Search for particles with unexpected mass and charge in Z decays"}],"external_system_identifiers":[{"schema":"CDS","value":"244602"},{"schema":"SPIRES","value":"SPIRES-2704242"}]},"created":"1993-03-08T00:00:00+00:00"},{"updated":"2021-03-19T16:51:11.697177+00:00","id":"341723","links":{"bibtex":"https://inspirehep.net/api/literature/341723?format=bibtex","latex-eu":"https://inspirehep.net/api/literature/341723?format=latex-eu","latex-us":"https://inspirehep.net/api/literature/341723?format=latex-us","json":"https://inspirehep.net/api/literature/341723?format=json","citations":"https://inspirehep.net/api/literature/?q=refersto%3Arecid%3A341723"},"metadata":{"report_numbers":[{"value":"CERN-PPE-92-184"}],"publication_info":[{"journal_volume":"298","page_end":"491","year":1993,"page_start":"479","journal_title":"Phys.Lett.B"}],"texkeys":["Buskulic:1992um"],"keywords":[{"schema":"PDG","source":"PDG","value":"S051:Desig=172"},{"schema":"INSPIRE","value":"electron positron: colliding beams"},{"schema":"INSPIRE","value":"colliding beams: electron positron"},{"schema":"INSPIRE","value":"electron positron: annihilation"},{"schema":"INSPIRE","value":"annihilation: electron positron"},{"schema":"INSPIRE","value":"Z0: electroproduction"},{"schema":"INSPIRE","value":"electroproduction: Z0"},{"schema":"INSPIRE","value":"Z0: nonleptonic decay"},{"schema":"INSPIRE","value":"nonleptonic decay: Z0"},{"schema":"INSPIRE","value":"bottom: pair production"},{"schema":"INSPIRE","value":"pair production: bottom"},{"schema":"INSPIRE","value":"bottom: decay modes"},{"schema":"INSPIRE","value":"decay modes: bottom"},{"schema":"INSPIRE","value":"bottom: branching ratio"},{"schema":"INSPIRE","value":"ALEPH"},{"schema":"INSPIRE","value":"experimental results"},{"schema":"INSPIRE","value":"CERN LEP Stor"},{"schema":"INSPIRE","value":"approx. 91 GeV-cms"}],"collaborations":[{"value":"ALEPH"}],"control_number":341723,"dois":[{"value":"10.1016/0370-2693(93)91853-F"}],"preprint_date":"1992-10","titles":[{"title":"Measurement of the b ---> tau- anti-tau-neutrino X branching ratio"},{"title":"ANTI-TAU NEUTRINO"}],"external_system_identifiers":[{"schema":"CDS","value":"243305"},{"schema":"SPIRES","value":"SPIRES-2665565"}]},"created":"1992-12-28T00:00:00+00:00"},{"updated":"2021-03-19T16:51:16.774027+00:00","id":"341556","links":{"bibtex":"https://inspirehep.net/api/literature/341556?format=bibtex","latex-eu":"https://inspirehep.net/api/literature/341556?format=latex-eu","latex-us":"https://inspirehep.net/api/literature/341556?format=latex-us","json":"https://inspirehep.net/api/literature/341556?format=json","citations":"https://inspirehep.net/api/literature/?q=refersto%3Arecid%3A341556"},"metadata":{"report_numbers":[{"value":"CERN-PPE-92-143"}],"publication_info":[{"journal_volume":"57","page_end":"36","year":1993,"page_start":"17","journal_title":"Z.Phys.C"}],"texkeys":["Buskulic:1992ji"],"keywords":[{"schema":"INSPIRE","value":"electron positron: colliding beams"},{"schema":"INSPIRE","value":"colliding beams: electron positron"},{"schema":"INSPIRE","value":"electron positron: annihilation"},{"schema":"INSPIRE","value":"annihilation: electron positron"},{"schema":"INSPIRE","value":"Z0: electroproduction"},{"schema":"INSPIRE","value":"electroproduction: Z0"},{"schema":"INSPIRE","value":"Z0: nonleptonic decay"},{"schema":"INSPIRE","value":"nonleptonic decay: Z0"},{"schema":"INSPIRE","value":"photon: direct production"},{"schema":"INSPIRE","value":"direct production: photon"},{"schema":"INSPIRE","value":"quark: bremsstrahlung"},{"schema":"INSPIRE","value":"bremsstrahlung: quark"},{"schema":"INSPIRE","value":"final-state interaction"},{"schema":"INSPIRE","value":"showers: parton"},{"schema":"INSPIRE","value":"leading logarithm approximation"},{"schema":"INSPIRE","value":"angular correlation: (jet photon)"},{"schema":"INSPIRE","value":"energy spectrum: (photon)"},{"schema":"INSPIRE","value":"(photon): energy spectrum"},{"schema":"INSPIRE","value":"transverse energy: spectrum"},{"schema":"INSPIRE","value":"spectrum: transverse energy"},{"schema":"INSPIRE","value":"ALEPH"},{"schema":"INSPIRE","value":"experimental results"},{"schema":"INSPIRE","value":"CERN LEP Stor"},{"schema":"INSPIRE","value":"electron positron --> (n)jet photon"},{"schema":"INSPIRE","value":"88-95 GeV-cms"}],"collaborations":[{"value":"ALEPH"}],"control_number":341556,"dois":[{"value":"10.1007/BF01555735"}],"preprint_date":"1992-08","titles":[{"title":"Measurement of prompt photon production in hadronic Z decays"}],"external_system_identifiers":[{"schema":"CDS","value":"241432"},{"schema":"SPIRES","value":"SPIRES-2663376"}]},"created":"1992-12-18T00:00:00+00:00"}],"total":18},"links":{"self":"https://inspirehep.net/api/literature/?sort=mostrecent&q=collaborations.value%3Aaleph+and+publication_info.year%3A1993+and+publication_info.journal_title%3A%2A+and+not+publication_info.cnum%3A%2A+and+author_count%3A100%2B&size=1000&page=1&fields=titles,publication_info,dois,texkeys,keywords,arxiv_preprints,collaborations,report_numbers,external_system_identifiers,imprints,preprint_date,arxiv_eprints","bibtex":"https://inspirehep.net/api/literature/?sort=mostrecent&q=collaborations.value%3Aaleph+and+publication_info.year%3A1993+and+publication_info.journal_title%3A%2A+and+not+publication_info.cnum%3A%2A+and+author_count%3A100%2B&size=1000&page=1&format=bibtex","latex-eu":"https://inspirehep.net/api/literature/?sort=mostrecent&q=collaborations.value%3Aaleph+and+publication_info.year%3A1993+and+publication_info.journal_title%3A%2A+and+not+publication_info.cnum%3A%2A+and+author_count%3A100%2B&size=1000&page=1&format=latex-eu","latex-us":"https://inspirehep.net/api/literature/?sort=mostrecent&q=collaborations.value%3Aaleph+and+publication_info.year%3A1993+and+publication_info.journal_title%3A%2A+and+not+publication_info.cnum%3A%2A+and+author_count%3A100%2B&size=1000&page=1&format=latex-us","json":"https://inspirehep.net/api/literature/?sort=mostrecent&q=collaborations.value%3Aaleph+and+publication_info.year%3A1993+and+publication_info.journal_title%3A%2A+and+not+publication_info.cnum%3A%2A+and+author_count%3A100%2B&size=1000&page=1&fields=titles,publication_info,dois,texkeys,keywords,arxiv_preprints,collaborations,report_numbers,external_system_identifiers,imprints,preprint_date,arxiv_eprints&format=json"}}